kronicle/__init__.py
kronicle/connectors/__init__.py
kronicle/connectors/abc_connector.py
kronicle/connectors/kronicle_reader.py
kronicle/connectors/kronicle_setup.py
kronicle/connectors/kronicle_writer.py
kronicle/models/__init__.py
kronicle/models/iso_datetime.py
kronicle/models/kronicable_sample.py
kronicle/models/kronicable_sample_collection.py
kronicle/models/kronicable_type.py
kronicle/models/kronicle_errors.py
kronicle/models/kronicle_payload.py
kronicle/utils/date_generator.py
kronicle/utils/dict_utils.py
kronicle/utils/file_utils.py
kronicle/utils/log.py
kronicle/utils/str_utils.py
kronicle_sdk-0.1.12.dist-info/METADATA
kronicle_sdk-0.1.12.dist-info/WHEEL
kronicle_sdk-0.1.12.dist-info/top_level.txt
kronicle_sdk-0.1.12.dist-info/RECORD
